discord/ext/customs/commands/__init__.py
discord.customs-1.0.2.dist-info/METADATA
discord.customs-1.0.2.dist-info/WHEEL
discord.customs-1.0.2.dist-info/top_level.txt
discord.customs-1.0.2.dist-info/RECORD
