Metadata-Version: 2.1
Name: discord.customs
Version: 1.0.2
Summary: A small pypi project, that adds more extensions to your discord.py bot.
Home-page: https://github.com/FrostiiWeeb/
Author: Alex Hutz
Author-email: frostiiweeb@gmail.com
License: MIT
Keywords: extensions,dpy,discord.py,discord
Platform: UNKNOWN
Classifier: Development Status :: 3 - Alpha
Classifier: Intended Audience :: Developers
Classifier: Topic :: Software Development :: Build Tools
Classifier: License :: OSI Approved :: MIT License
Classifier: Programming Language :: Python :: 3
Classifier: Programming Language :: Python :: 3.4
Classifier: Programming Language :: Python :: 3.5
Classifier: Programming Language :: Python :: 3.6
